setup.py
dist_binom_gauss/Binomialdistribution.py
dist_binom_gauss/Gaussiandistribution.py
dist_binom_gauss/Generaldistribution.py
dist_binom_gauss/__init__.py
dist_binom_gauss.egg-info/PKG-INFO
dist_binom_gauss.egg-info/SOURCES.txt
dist_binom_gauss.egg-info/dependency_links.txt
dist_binom_gauss.egg-info/not-zip-safe
dist_binom_gauss.egg-info/top_level.txt