Metadata-Version: 1.0
Name: dist-binom-gauss
Version: 1.0
Summary: Gaussian and binomial distributions
Home-page: UNKNOWN
Author: Pedro Ignacio Rocha
Author-email: rochapedroignacio@gmail.com
License: UNKNOWN
Platform: UNKNOWN
